mehanika_robota/__init__.py
mehanika_robota/_alati.py
mehanika_robota/test.py
mehanika_robota/mehanika/__init__.py
mehanika_robota/mehanika/kinematika.py
mehanika_robota/mehanika/mat_prostor.py
mehanika_robota/mehanika/trajektorija.py
mehanika_robota/roboti/__init__.py
mehanika_robota/roboti/niryo_one/__init__.py
mehanika_robota/roboti/niryo_one/niryo_one.py
mehanika_robota/test/__init__.py
mehanika_robota/test/test__alati.py
mehanika_robota/test/test_kinematika.py
mehanika_robota/test/test_mat_prostor.py
mehanika_robota/test/test_niryo_one.py
mehanika_robota/test/test_trajektorija.py
mehanika_robota-2025.4.21.dist-info/licenses/LICENSE
mehanika_robota-2025.4.21.dist-info/METADATA
mehanika_robota-2025.4.21.dist-info/WHEEL
mehanika_robota-2025.4.21.dist-info/top_level.txt
mehanika_robota-2025.4.21.dist-info/RECORD
