Metadata-Version: 2.4
Name: mehanika_robota
Version: 2025.4.21
Summary: Biblioteka za proracun mehanike robota
Author-email: Vuk Todorovic <vuk.todorovic01@gmail.com>
Maintainer-email: Vuk Todorovic <vuk.todorovic01@gmail.com>
License:                     GNU GENERAL PUBLIC LICENSE
Project-URL: homepage, https://github.com/VuckoT/mehanika_robota
Project-URL: documentation, https://github.com/VuckoT/mehanika_robota
Project-URL: source, https://github.com/VuckoT/mehanika_robota/mehanika_robota
Keywords: mehanika,roboti,robotika,inverzna kinematika
Classifier: License :: OSI Approved :: GNU General Public License v3 (GPLv3)
Classifier: Operating System :: OS Independent
Classifier: Natural Language :: Serbian
Classifier: Programming Language :: Python :: 3.12
Classifier: Topic :: Education :: Testing
Classifier: Topic :: Scientific/Engineering :: Mathematics
Requires-Python: >=3.12
License-File: LICENSE
Requires-Dist: numpy
Requires-Dist: pyniryo
Requires-Dist: pytest
Requires-Dist: ruff
Dynamic: license-file
